prepackage/__init__.py
prepackage/prepackage.py
prepackage-0.0.2.dist-info/METADATA
prepackage-0.0.2.dist-info/WHEEL
prepackage-0.0.2.dist-info/top_level.txt
prepackage-0.0.2.dist-info/RECORD
