Metadata-Version: 2.1
Name: prepackage
Version: 0.0.2
Summary: prepackage
Home-page: UNKNOWN
Author: jaytrairat
Author-email: <jay.trairat@gmail.com>
License: UNKNOWN
Keywords: jaytrairat
Platform: UNKNOWN
Classifier: Programming Language :: Python :: 3
